{
  "version": "1.0.0",
  "rss": "https://votre-serveur.com/modpacks/notifications.xml",
  "discord": {
    "clientId": "<FILL IN OR REMOVE DISCORD OBJECT>",
    "smallImageText": "<FILL IN OR REMOVE DISCORD OBJECT>",
    "smallImageKey": "<FILL IN OR REMOVE DISCORD OBJECT>"
  },
  "servers": [
    {
      "id": "modpack",
      "name": "Modpack",
      "description": "Modpack Modpack version 1.0.0 running Minecraft 1.21.1",
      "icon": "https://votre-serveur.com/modpacks/icon.png",
      "version": "1.0.0",
      "address": "localhost:25565",
      "minecraftVersion": "1.21.1",
      "mainServer": true,
      "autoconnect": true,
      "modules": [
        {
          "id": "net.minecraft:client:1.21.1",
          "name": "Minecraft 1.21.1",
          "type": "Version",
          "artifact": {
            "size": 26836906,
            "MD5": "0b90a83eb9910468c60152f6594b9271",
            "url": "https://votre-serveur.com/modpacks/versions/1.21.1/1.21.1.jar"
          }
        },
        {
          "id": "net.neoforged:neoforge:21.1.186",
          "name": "NeoForge",
          "type": "ForgeHosted",
          "artifact": {
            "size": 6923917,
            "MD5": "2973791629522b511192ef66c285758d",
            "url": "https://votre-serveur.com/modpacks/bin/neoforge-1.21.1-47.0.20.jar"
          },
          "subModules": [
            {
              "id": "1.21.1-neoforge-21.1.186",
              "name": "NeoForge (version.json)",
              "type": "VersionManifest",
              "artifact": {
                "size": 862,
                "MD5": "7cab7eed1cb1ee67fcd9b951be562191",
                "url": "https://votre-serveur.com/modpacks/versions/1.21.1-neoforge-21.1.186/1.21.1-neoforge-21.1.186.json"
              }
            }
          ]
        },
        {
          "id": "generated.neoforgemod:copycats:3.0.2+mc.1.21.1-neoforge@jar",
          "name": "copycats-3.0.2+mc.1.21.1-neoforge",
          "type": "ForgeMod",
          "artifact": {
            "size": 1790416,
            "url": "https://votre-serveur.com/modpacks/mods/copycats-3.0.2+mc.1.21.1-neoforge.jar",
            "MD5": "cde8b4432b19fde830c50ce07a2b89b9"
          }
        },
        {
          "id": "generated.neoforgemod:create:1.21.1-6.0.6@jar",
          "name": "create-1.21.1-6.0.6",
          "type": "ForgeMod",
          "artifact": {
            "size": 18599196,
            "url": "https://votre-serveur.com/modpacks/mods/create-1.21.1-6.0.6.jar",
            "MD5": "39db2efac7c0482c2c1bfdbaaab317b3"
          }
        },
        {
          "id": "generated.neoforgemod:creativecore_neoforge_v2.13.7_mc1.21.1:1.0.0@jar",
          "name": "CreativeCore_NEOFORGE_v2.13.7_mc1.21.1",
          "type": "ForgeMod",
          "artifact": {
            "size": 1206816,
            "url": "https://votre-serveur.com/modpacks/mods/CreativeCore_NEOFORGE_v2.13.7_mc1.21.1.jar",
            "MD5": "9824bb8cd69f94d5cd698cd998113eb7"
          }
        },
        {
          "id": "generated.neoforgemod:Essential_1:3-8-4_neoforge_1-21-1@jar",
          "name": "Essential_1-3-8-4_neoforge_1-21-1",
          "type": "ForgeMod",
          "artifact": {
            "size": 53625713,
            "url": "https://votre-serveur.com/modpacks/mods/Essential_1-3-8-4_neoforge_1-21-1.jar",
            "MD5": "7704173d48743103b7067501150dc89f"
          }
        },
        {
          "id": "generated.neoforgemod:ferritecore:7.0.2-neoforge@jar",
          "name": "ferritecore-7.0.2-neoforge",
          "type": "ForgeMod",
          "artifact": {
            "size": 118911,
            "url": "https://votre-serveur.com/modpacks/mods/ferritecore-7.0.2-neoforge.jar",
            "MD5": "e176f7b9672b5b36130dc2f46ea96f48"
          }
        },
        {
          "id": "generated.neoforgemod:iris:neoforge-1.8.12+mc1.21.1@jar",
          "name": "iris-neoforge-1.8.12+mc1.21.1",
          "type": "ForgeMod",
          "artifact": {
            "size": 2438548,
            "url": "https://votre-serveur.com/modpacks/mods/iris-neoforge-1.8.12+mc1.21.1.jar",
            "MD5": "6c1122aa7c2b1a4f24831e394c5b513f"
          }
        },
        {
          "id": "generated.neoforgemod:lithium:neoforge-0.15.0+mc1.21.1@jar",
          "name": "lithium-neoforge-0.15.0+mc1.21.1",
          "type": "ForgeMod",
          "artifact": {
            "size": 747405,
            "url": "https://votre-serveur.com/modpacks/mods/lithium-neoforge-0.15.0+mc1.21.1.jar",
            "MD5": "429c693999fad17d6fe35f2aeea92b18"
          }
        },
        {
          "id": "generated.neoforgemod:sodium:neoforge-0.6.13+mc1.21.1@jar",
          "name": "sodium-neoforge-0.6.13+mc1.21.1",
          "type": "ForgeMod",
          "artifact": {
            "size": 1162994,
            "url": "https://votre-serveur.com/modpacks/mods/sodium-neoforge-0.6.13+mc1.21.1.jar",
            "MD5": "e5018c782d851fea76be0205b7616e5d"
          }
        },
        {
          "id": "generated.neoforgemod:waterframes:NEOFORGE-mc1.21.1-v2.1.15@jar",
          "name": "waterframes-NEOFORGE-mc1.21.1-v2.1.15",
          "type": "ForgeMod",
          "artifact": {
            "size": 245059,
            "url": "https://votre-serveur.com/modpacks/mods/waterframes-NEOFORGE-mc1.21.1-v2.1.15.jar",
            "MD5": "a583eae74a0b3ea802b4e7519d88129a"
          }
        },
        {
          "id": "generated.neoforgemod:watermedia:2.1.25@jar",
          "name": "watermedia-2.1.25",
          "type": "ForgeMod",
          "artifact": {
            "size": 37854313,
            "url": "https://votre-serveur.com/modpacks/mods/watermedia-2.1.25.jar",
            "MD5": "b6a86c0336d0cebce6a3738ef26bb81c"
          }
        },
        {
          "id": "generated.file:shaderpacks:1.0.0@zip",
          "name": "Shaderpacks Pack",
          "type": "File",
          "artifact": {
            "size": 401179,
            "MD5": "0c40993f3c8e3b4beec7b7886f566616",
            "url": "https://votre-serveur.com/modpacks/shaderpacks.zip",
            "path": "shaderpacks/"
          }
        },
        {
          "id": "generated.file:shaderpacks:1.0.0@zip",
          "name": "shaderpacks Custom Pack",
          "type": "File",
          "artifact": {
            "size": 401179,
            "MD5": "0c40993f3c8e3b4beec7b7886f566616",
            "url": "https://votre-serveur.com/modpacks/shaderpacks_custom.zip",
            "path": "shaderpacks/"
          }
        }
      ]
    }
  ]
}